biu/__init__.py
biu-0.3.0.dist-info/METADATA
biu-0.3.0.dist-info/WHEEL
biu-0.3.0.dist-info/licenses/LICENSE
biu-0.3.0.dist-info/RECORD
