Metadata-Version: 2.3
Name: biu
Version: 0.3.0
Summary: tiny web crawler
License-File: LICENSE
Requires-Python: >=3.9
Requires-Dist: gevent>=24.2.1
Requires-Dist: parsel>=1.9.1
Requires-Dist: requests>=2.32.3
